click_commands_folder/__init__.py
click_commands_folder/commands_folder.py
click_commands_folder-1.0.1.dist-info/LICENSE
click_commands_folder-1.0.1.dist-info/METADATA
click_commands_folder-1.0.1.dist-info/WHEEL
click_commands_folder-1.0.1.dist-info/top_level.txt
click_commands_folder-1.0.1.dist-info/RECORD
