Metadata-Version: 2.1
Name: click-commands-folder
Version: 1.0.1
Summary: A Click extension to read commands from a folder
Author-email: rotoclap <rotoclap@gmail.com>
License: MIT License
Project-URL: Homepage, https://github.com/rotoclap/click-commands-folder
Project-URL: Documentation, https://click-commands-folder.readthedocs.io
Project-URL: Issues, https://github.com/rotoclap/click-commands-folder/issues
Keywords: click,command,folder
Classifier: Development Status :: 5 - Production/Stable
Classifier: Intended Audience :: Developers
Classifier: Environment :: Console
Classifier: Programming Language :: Python :: 3
Classifier: License :: OSI Approved :: MIT License
Classifier: Operating System :: OS Independent
Requires-Python: >=3.8
License-File: LICENSE
Requires-Dist: click
